statick_tool/plugins/tool/fortify_plugin/__init__.py
statick_tool/plugins/tool/fortify_plugin/fortify_tool_plugin.py
statick_tool/plugins/tool/fortify_plugin/fortify_tool_plugin.yapsy-plugin
statick_tool/rsc/plugin_mapping/fortify.txt
statick_fortify-0.1.5.dist-info/LICENSE.md
statick_fortify-0.1.5.dist-info/METADATA
statick_fortify-0.1.5.dist-info/WHEEL
statick_fortify-0.1.5.dist-info/top_level.txt
statick_fortify-0.1.5.dist-info/RECORD
