Metadata-Version: 2.1
Name: statick-fortify
Version: 0.1.5
Summary: Statick extension to integrate Fortify.
Home-page: https://github.com/soartech/statick-fortify
Author: Soar Technology, Inc.
License: UNKNOWN
Platform: UNKNOWN
Classifier: License :: OSI Approved :: BSD License
Classifier: Programming Language :: Python :: 2.7
Classifier: Programming Language :: Python :: 3.4
Classifier: Programming Language :: Python :: 3.5
Classifier: Programming Language :: Python :: 3.6
Classifier: Programming Language :: Python :: 3.7
Classifier: Topic :: Software Development :: Testing
Requires-Dist: statick
Requires-Dist: backports.tempfile
Provides-Extra: test
Requires-Dist: pytest ; extra == 'test'
Requires-Dist: mock ; extra == 'test'
